dirai/__init__.py
dirai/dirai.py
dirai-0.0.6.dist-info/METADATA
dirai-0.0.6.dist-info/WHEEL
dirai-0.0.6.dist-info/top_level.txt
dirai-0.0.6.dist-info/RECORD
