Metadata-Version: 2.1
Name: dirai
Version: 0.0.6
Summary: DIRAI API
Home-page: UNKNOWN
Author: SOMMA Investimentos
Author-email: <vitor.alves@sommainvestimentos.com>
License: UNKNOWN
Keywords: python,dirai
Platform: UNKNOWN
Classifier: Development Status :: 1 - Planning
Classifier: Intended Audience :: Developers
Classifier: Programming Language :: Python :: 3
Classifier: Operating System :: Unix
Classifier: Operating System :: MacOS :: MacOS X
Classifier: Operating System :: Microsoft :: Windows
Requires-Dist: pymysql
Requires-Dist: cryptography
Requires-Dist: pandas
